snekoil/__init__.py
snekoil/iterators.py
snekoil/snekpatch.py
snekoil/speedup.py
snekoil/time.py
snekoil/unsnekpatch.py
snekoil-0.6.0.dist-info/LICENSE
snekoil-0.6.0.dist-info/METADATA
snekoil-0.6.0.dist-info/WHEEL
snekoil-0.6.0.dist-info/RECORD
