Metadata-Version: 2.1
Name: snekoil
Version: 0.6.0
Summary: Unreasonably fast
License: ISC
Author: overflowerror
Author-email: mail@overflowerror.com
Requires-Python: >=3.11,<4.0
Classifier: License :: OSI Approved
Classifier: Programming Language :: Python :: 3
Classifier: Programming Language :: Python :: 3.11
Classifier: Programming Language :: Python :: 3.12
Requires-Dist: pytest-cov (>=4.1.0,<5.0.0)
